src/__init__.py
src/Utils/Mongo_conn.py
src/Utils/MyUtils.py
src/Utils/Rabbit_conn.py
src/Utils/Redis_conn.py
src/Utils/__init__.py
src/Utils/monitor_rabbit.py
src/Utils/proxy.py
zhan_lan-0.1.0.dist-info/LICENSE
zhan_lan-0.1.0.dist-info/METADATA
zhan_lan-0.1.0.dist-info/WHEEL
zhan_lan-0.1.0.dist-info/top_level.txt
zhan_lan-0.1.0.dist-info/RECORD
